libreriaclases.py
libreriaclases-3.8.dist-info/METADATA
libreriaclases-3.8.dist-info/WHEEL
libreriaclases-3.8.dist-info/licenses/LICENSE
libreriaclases-3.8.dist-info/RECORD
