Metadata-Version: 2.4
Name: libreriaclases
Version: 3.8
Summary: Libreria preproceso
Project-URL: Homepage, https://github.com/uxueballarin/PBLgrupo6
Project-URL: Bug Tracker, https://github.com/uxueballarin/PBLgrupo6/issues
Author-email: uxueballarin <uxue.ballarin@alumni.mondragon.edu>
License: MIT License
License-File: LICENSE
Classifier: License :: OSI Approved :: MIT License
Classifier: Operating System :: OS Independent
Classifier: Programming Language :: Python :: 3
Requires-Python: >=4.0
